ledgerloom/__init__.py
ledgerloom/__main__.py
ledgerloom/artifacts.py
ledgerloom/chart.py
ledgerloom/cli.py
ledgerloom/core.py
ledgerloom/docs_helper.py
ledgerloom/io_jsonl.py
ledgerloom/paths.py
ledgerloom/reports.py
ledgerloom/chapters/__init__.py
ledgerloom/chapters/ch01_journal_vs_eventlog.py
ledgerloom/chapters/ch02_debits_credits_encoding.py
ledgerloom/chapters/ch03_chart_of_accounts_schema.py
ledgerloom/chapters/ch03_posting_to_ledger.py
ledgerloom/chapters/ch04_general_ledger_database.py
ledgerloom/chapters/ch05_accounting_equation_invariant.py
ledgerloom/chapters/ch06_periods_accrual_timing.py
ledgerloom/chapters/ch07_adjusting_entries_late_arriving_data.py
ledgerloom/chapters/ch085_opening_next_period.py
ledgerloom/chapters/ch08_closing_controlled_transformation.py
ledgerloom/chapters/ch09_ar_lifecycle.py
ledgerloom/chapters/ch10_ap_lifecycle.py
ledgerloom/chapters/ch11_inventory_cogs.py
ledgerloom/chapters/ch12_fixed_assets_depreciation.py
ledgerloom/chapters/ch13_payroll_register.py
ledgerloom/engine/__init__.py
ledgerloom/engine/closing_entries.py
ledgerloom/engine/coa.py
ledgerloom/engine/config.py
ledgerloom/engine/ledger.py
ledgerloom/engine/money.py
ledgerloom/ingest/__init__.py
ledgerloom/ingest/csv_bank_feed.py
ledgerloom/ingest/csv_journal_entries.py
ledgerloom/ingest/models.py
ledgerloom/project/__init__.py
ledgerloom/project/build.py
ledgerloom/project/check.py
ledgerloom/project/coa.py
ledgerloom/project/config.py
ledgerloom/project/init.py
ledgerloom/project/paths.py
ledgerloom/project/reclass.py
ledgerloom/project/suggest_mappings.py
ledgerloom/scenarios/__init__.py
ledgerloom/scenarios/bookset_v1.py
ledgerloom/trust/__init__.py
ledgerloom/trust/pipeline.py
ledgerloom-0.3.0.dist-info/licenses/LICENSE
ledgerloom-0.3.0.dist-info/METADATA
ledgerloom-0.3.0.dist-info/WHEEL
ledgerloom-0.3.0.dist-info/entry_points.txt
ledgerloom-0.3.0.dist-info/top_level.txt
ledgerloom-0.3.0.dist-info/RECORD
