Metadata-Version: 2.4
Name: ledgerloom
Version: 0.3.0
Summary: LedgerLoom: accounting concepts for the modern software mind.
Author: PyStatsV1
License-Expression: MIT
Project-URL: Homepage, https://github.com/pystatsv1/ledgerloom
Project-URL: Repository, https://github.com/pystatsv1/ledgerloom
Project-URL: Issues, https://github.com/pystatsv1/ledgerloom/issues
Project-URL: Documentation, https://ledgerloom.readthedocs.io
Project-URL: Changelog, https://github.com/pystatsv1/ledgerloom/blob/main/CHANGELOG.md
Keywords: accounting,bookkeeping,double-entry,ledger,event-sourcing,education
Classifier: Development Status :: 4 - Beta
Classifier: Intended Audience :: Developers
Classifier: Intended Audience :: Education
Classifier: Programming Language :: Python :: 3
Classifier: Programming Language :: Python :: 3 :: Only
Classifier: Programming Language :: Python :: 3.10
Classifier: Programming Language :: Python :: 3.11
Classifier: Programming Language :: Python :: 3.12
Classifier: Topic :: Office/Business :: Financial :: Accounting
Classifier: Topic :: Education
Classifier: Topic :: Software Development :: Libraries :: Python Modules
Requires-Python: >=3.10
License-File: LICENSE
Requires-Dist: pandas>=2.0
Requires-Dist: pyyaml>=6.0
Provides-Extra: dev
Requires-Dist: pytest>=7; extra == "dev"
Requires-Dist: ruff>=0.6; extra == "dev"
Requires-Dist: build>=1.2; extra == "dev"
Requires-Dist: twine>=5; extra == "dev"
Provides-Extra: docs
Requires-Dist: sphinx>=7; extra == "docs"
Requires-Dist: sphinx-rtd-theme>=2; extra == "docs"
Dynamic: license-file
